{
  "indexes": [
    {
      "collectionGroup": "applications",
      "queryScope": "COLLECTION",
      "fields": [
        { "fieldPath": "candidateEmail", "order": "ASCENDING" },
        { "fieldPath": "status", "order": "ASCENDING" },
        { "fieldPath": "stage", "order": "ASCENDING" }
      ]
    },
    {
      "collectionGroup": "emailLogs",
      "queryScope": "COLLECTION",
      "fields": [
        { "fieldPath": "candidateId", "order": "ASCENDING" },
        { "fieldPath": "attemptedAt", "order": "DESCENDING" }
      ]
    },
    {
      "collectionGroup": "emailLogs",
      "queryScope": "COLLECTION",
      "fields": [
        { "fieldPath": "applicationId", "order": "ASCENDING" },
        { "fieldPath": "status", "order": "ASCENDING" },
        { "fieldPath": "attemptedAt", "order": "DESCENDING" }
      ]
    },
    {
      "collectionGroup": "emailLogs",
      "queryScope": "COLLECTION",
      "fields": [
        { "fieldPath": "status", "order": "ASCENDING" },
        { "fieldPath": "attemptedAt", "order": "DESCENDING" }
      ]
    }
  ],
  "fieldOverrides": []
}
